devenv/TestHarness.py
devenv/__init__.py
examples/__init__.py
examples/example.py
reahl/tofu/__init__.py
reahl/tofu/checks.py
reahl/tofu/files.py
reahl/tofu/fixture.py
reahl/tofu/pytestsupport.py
reahl/tofu_dev/__init__.py
reahl/tofu_dev/test_fixture.py
reahl/tofu_dev/test_pytestsupport.py
tofu_test/__init__.py
tofu_test/mod.py
reahl_tofu-7.0.3.dist-info/LICENSE
reahl_tofu-7.0.3.dist-info/METADATA
reahl_tofu-7.0.3.dist-info/WHEEL
reahl_tofu-7.0.3.dist-info/reahl-component.toml
reahl_tofu-7.0.3.dist-info/top_level.txt
reahl_tofu-7.0.3.dist-info/RECORD
