Metadata-Version: 2.1
Name: reahl-tofu
Version: 7.0.3
Summary: A testing framework that couples fixtures and tests loosely.
Author-email: Iwan Vosloo <iwan@reahl.org>, Craig Sparks <craig@reahl.org>
Classifier: Development Status :: 5 - Production/Stable
Classifier: Intended Audience :: Developers
Classifier: License :: OSI Approved
Classifier: Operating System :: OS Independent
Classifier: Programming Language :: Python :: 3
Classifier: Topic :: Software Development :: Testing
Requires-Python: >=3.8
License-File: LICENSE
Requires-Dist: reahl-component <7.1,>=7.0
Requires-Dist: wrapt <1.16.999,>=1.11.0
Provides-Extra: test
Requires-Dist: pytest >=3.0 ; extra == 'test'
